rasa_nlu/__init__.py
rasa_nlu/components.py
rasa_nlu/config.py
rasa_nlu/convert.py
rasa_nlu/data_router.py
rasa_nlu/evaluate.py
rasa_nlu/model.py
rasa_nlu/persistor.py
rasa_nlu/project.py
rasa_nlu/registry.py
rasa_nlu/run.py
rasa_nlu/server.py
rasa_nlu/test.py
rasa_nlu/train.py
rasa_nlu/version.py
rasa_nlu/classifiers/__init__.py
rasa_nlu/classifiers/embedding_intent_classifier.py
rasa_nlu/classifiers/keyword_intent_classifier.py
rasa_nlu/classifiers/mitie_intent_classifier.py
rasa_nlu/classifiers/sklearn_intent_classifier.py
rasa_nlu/cli/__init__.py
rasa_nlu/cli/server.py
rasa_nlu/emulators/__init__.py
rasa_nlu/emulators/dialogflow.py
rasa_nlu/emulators/luis.py
rasa_nlu/emulators/wit.py
rasa_nlu/extractors/__init__.py
rasa_nlu/extractors/crf_entity_extractor.py
rasa_nlu/extractors/duckling_http_extractor.py
rasa_nlu/extractors/entity_synonyms.py
rasa_nlu/extractors/mitie_entity_extractor.py
rasa_nlu/extractors/spacy_entity_extractor.py
rasa_nlu/featurizers/__init__.py
rasa_nlu/featurizers/count_vectors_featurizer.py
rasa_nlu/featurizers/mitie_featurizer.py
rasa_nlu/featurizers/ngram_featurizer.py
rasa_nlu/featurizers/regex_featurizer.py
rasa_nlu/featurizers/spacy_featurizer.py
rasa_nlu/tokenizers/__init__.py
rasa_nlu/tokenizers/jieba_tokenizer.py
rasa_nlu/tokenizers/mitie_tokenizer.py
rasa_nlu/tokenizers/spacy_tokenizer.py
rasa_nlu/tokenizers/whitespace_tokenizer.py
rasa_nlu/training_data/__init__.py
rasa_nlu/training_data/loading.py
rasa_nlu/training_data/message.py
rasa_nlu/training_data/training_data.py
rasa_nlu/training_data/util.py
rasa_nlu/training_data/formats/__init__.py
rasa_nlu/training_data/formats/dialogflow.py
rasa_nlu/training_data/formats/luis.py
rasa_nlu/training_data/formats/markdown.py
rasa_nlu/training_data/formats/rasa.py
rasa_nlu/training_data/formats/readerwriter.py
rasa_nlu/training_data/formats/wit.py
rasa_nlu/utils/__init__.py
rasa_nlu/utils/mitie_utils.py
rasa_nlu/utils/spacy_utils.py
rasa_nlu_contrib-0.16.1.dist-info/LICENSE
rasa_nlu_contrib-0.16.1.dist-info/METADATA
rasa_nlu_contrib-0.16.1.dist-info/WHEEL
rasa_nlu_contrib-0.16.1.dist-info/top_level.txt
rasa_nlu_contrib-0.16.1.dist-info/RECORD
