Metadata-Version: 2.1
Name: rasa-nlu-contrib
Version: 0.16.1
Summary: Rasa NLU engine backported from main Rasa project
Home-page: https://github.com/madkote/rasa-nlu-contrib
Download-URL: https://github.com/madkote/rasa-nlu-contrib/archive/0.16.1.tar.gz
Author: madkote
Author-email: madkote <madkote@bluewin.ch>
License: MIT / Apache 2.0
Project-URL: Bug Reports, https://github.com/madkote/rasa_nlu_contrib/issues
Project-URL: Source, https://github.com/madkote/rasa_nlu_contrib
Keywords: nlp,machine-learning,machine-learning-library,bot,bots,botkit,conversational-agents,conversational-ai,chatbot,chatbot-framework,bot-framework
Platform: any
Classifier: Programming Language :: Python
Classifier: Programming Language :: Python :: 3
Classifier: Programming Language :: Python :: 3.6
Classifier: Programming Language :: Python :: 3.7
Classifier: Intended Audience :: Developers
Classifier: License :: OSI Approved :: Apache Software License
Classifier: Operating System :: OS Independent
Classifier: Topic :: Software Development :: Libraries
Requires-Python: >=3.6, !=3.8.*, !=3.9.*, <4
License-File: LICENSE
Requires-Dist: cloudpickle (~=0.6.1)
Requires-Dist: coloredlogs (~=10.0)
Requires-Dist: future (~=0.17.1)
Requires-Dist: jsonschema (~=2.6.0)
Requires-Dist: matplotlib (~=2.2.4)
Requires-Dist: numpy (~=1.16.0)
Requires-Dist: packaging (~=18.0)
Requires-Dist: requests (~=2.20.0)
Requires-Dist: ruamel.yaml (~=0.15.78)
Requires-Dist: scikit-learn (~=0.20.2)
Requires-Dist: simplejson (~=3.13.2)
Requires-Dist: six (~=1.11.0)
Requires-Dist: tqdm (~=4.19.5)
Requires-Dist: typing (~=3.6.2)
Provides-Extra: all
Requires-Dist: hyperlink (~=17.3.1) ; extra == 'all'
Requires-Dist: klein (~=17.10.0) ; extra == 'all'
Requires-Dist: Twisted (==20.3.0) ; extra == 'all'
Requires-Dist: spacy (>2.0,~=2.0.18) ; extra == 'all'
Requires-Dist: scipy (~=1.2.0) ; extra == 'all'
Requires-Dist: sklearn-crfsuite (~=0.3.6) ; extra == 'all'
Requires-Dist: tensorflow (~=1.13.1) ; extra == 'all'
Provides-Extra: duckling
Requires-Dist: duckling (==1.8.0) ; extra == 'duckling'
Requires-Dist: Jpype1 (==0.6.2) ; extra == 'duckling'
Provides-Extra: mitie
Requires-Dist: mitie (==0.7.0) ; extra == 'mitie'
Provides-Extra: server
Requires-Dist: hyperlink (~=17.3.1) ; extra == 'server'
Requires-Dist: klein (~=17.10.0) ; extra == 'server'
Requires-Dist: Twisted (==20.3.0) ; extra == 'server'
Provides-Extra: spacy
Requires-Dist: spacy (>2.0,~=2.0.18) ; extra == 'spacy'
Requires-Dist: scipy (~=1.2.0) ; extra == 'spacy'
Requires-Dist: sklearn-crfsuite (~=0.3.6) ; extra == 'spacy'
Provides-Extra: tensorflow
Requires-Dist: tensorflow (~=1.13.1) ; extra == 'tensorflow'
Requires-Dist: scipy (~=1.2.0) ; extra == 'tensorflow'
Requires-Dist: sklearn-crfsuite (~=0.3.6) ; extra == 'tensorflow'
Provides-Extra: test
Requires-Dist: hyperlink (~=17.3.1) ; extra == 'test'
Requires-Dist: klein (~=17.10.0) ; extra == 'test'
Requires-Dist: Twisted (==20.3.0) ; extra == 'test'
Requires-Dist: bandit (~=1.7.0) ; extra == 'test'
Requires-Dist: docker-compose (~=1.28.0) ; extra == 'test'
Requires-Dist: flake8 (~=3.8.4) ; extra == 'test'
Requires-Dist: httpretty (~=0.9.5) ; extra == 'test'
Requires-Dist: mock (~=2.0.0) ; extra == 'test'
Requires-Dist: moto (~=1.3.8) ; extra == 'test'
Requires-Dist: python-coveralls (~=2.9.1) ; extra == 'test'
Requires-Dist: pytest (~=3.2.5) ; extra == 'test'
Requires-Dist: pytest-pycodestyle (~=1.4.0) ; extra == 'test'
Requires-Dist: pytest-cov (~=2.5.1) ; extra == 'test'
Requires-Dist: pytest-twisted (<1.6) ; extra == 'test'
Requires-Dist: responses (~=0.9.0) ; extra == 'test'
Requires-Dist: treq (~=17.8.0) ; extra == 'test'
Provides-Extra: zh
Requires-Dist: jieba (==0.39) ; extra == 'zh'
